cleanlizard/__init__.py
cleanlizard/appendstr.py
cleanlizard/exportliz.py
cleanlizard/getfiles.py
cleanlizard/liz_number.py
cleanlizard/liz_toes.py
cleanlizard/monthlit.py
cleanlizard/namefile.py
cleanlizard/prettyprint.py
cleanlizard/summary_functions.py
cleanlizard-0.1.4.dist-info/METADATA
cleanlizard-0.1.4.dist-info/WHEEL
cleanlizard-0.1.4.dist-info/top_level.txt
cleanlizard-0.1.4.dist-info/RECORD
